irtenwolco/__init__.py
irtenwolco/foobar.py
stam/__init__.py
stam/foobar.py
irtenwolco-0.0.2.dist-info/METADATA
irtenwolco-0.0.2.dist-info/WHEEL
irtenwolco-0.0.2.dist-info/top_level.txt
irtenwolco-0.0.2.dist-info/RECORD
