Metadata-Version: 2.1
Name: irtenwolco
Version: 0.0.2
Summary: foobar power
Author: Binyamin Haymann
Author-email: binyamin@ilrd.co.il
Keywords: python,good_practice
